Metadata-Version: 2.4
Name: spm-runtime-R2025b
Version: 25.1.2.post2
Summary: Compiled SPM package that can be called from Python
Maintainer-email: Yael Balbastre <y.balbastre@ucl.ac.uk>
License-Expression: GPL-2.0
Project-URL: Homepage, https://github.com/balbasty/spm-runtime
Project-URL: Issues, https://github.com/balbasty/spm-runtime/issues
Classifier: Intended Audience :: Science/Research
Classifier: Operating System :: OS Independent
Classifier: Programming Language :: Python :: 3.10
Classifier: Programming Language :: Python :: 3.11
Classifier: Programming Language :: Python :: 3.12
Classifier: Programming Language :: Python :: 3.13
Requires-Python: <3.14,>=3.10
License-File: LICENSE
Requires-Dist: matlab-runtime>=0.0.4
Provides-Extra: test
Requires-Dist: pytest; extra == "test"
Dynamic: license-file
